qubot/__init__.py
qubot/main.py
qubot/config/__init__.py
qubot/config/config.py
qubot/config/preset_rewards.py
qubot/config/qubot.py
qubot/driver/__init__.py
qubot/driver/driver.py
qubot/environment/__init__.py
qubot/environment/environment.py
qubot/environment/q_learning_environment.py
qubot/stats/__init__.py
qubot/stats/stats.py
qubot/ui/__init__.py
qubot/ui/ui_action.py
qubot/ui/ui_tree.py
qubot/utils/__init__.py
qubot/utils/errors.py
qubot/utils/input_generation.py
qubot/utils/io.py
qubot-0.0.13.dist-info/LICENSE.md
qubot-0.0.13.dist-info/METADATA
qubot-0.0.13.dist-info/WHEEL
qubot-0.0.13.dist-info/entry_points.txt
qubot-0.0.13.dist-info/top_level.txt
qubot-0.0.13.dist-info/RECORD
