Metadata-Version: 2.1
Name: qubot
Version: 0.0.13
Summary: Qubot automated testing framework.
Home-page: https://github.com/anthonykrivonos/qubot
Author: anthonykrivonos, kenkenchuen
Author-email: ak4483@columbia.edu, kc3334@columbia.edu
License: MIT
Platform: UNKNOWN
Requires-Python: >=3.7
Requires-Dist: numpy (>=1.20.2)
Requires-Dist: gym (>=0.18.0)
Requires-Dist: selenium (>=3.141.0)
Requires-Dist: Pillow (==6.2.2)
Requires-Dist: geckodriver-autoinstaller (==0.1.0)
Requires-Dist: timeout-decorator (==0.5.0)
